Metadata-Version: 2.1
Name: pure-data
Version: 0.1.6.5
Summary: Pure Data Framework
Home-page: https://github.com/SimulatorML/Pure-Data
Author: BOGDAN PECHENKIN
Author-email: uberkinder@yandex.com
License: UNKNOWN
Platform: UNKNOWN
Classifier: Programming Language :: Python :: 3
Classifier: License :: OSI Approved :: MIT License
Classifier: Operating System :: OS Independent
Requires-Python: >=3.10
License-File: LICENSE
